cvequery-1.0.6.post1.dist-info/licenses/LICENSE
src/__init__.py
src/__version__.py
src/api.py
src/cli.py
src/completion.py
src/constants.py
src/formatting.py
src/interactive.py
src/main.py
src/utils.py
cvequery-1.0.6.post1.dist-info/METADATA
cvequery-1.0.6.post1.dist-info/WHEEL
cvequery-1.0.6.post1.dist-info/entry_points.txt
cvequery-1.0.6.post1.dist-info/top_level.txt
cvequery-1.0.6.post1.dist-info/RECORD
