Metadata-Version: 2.4
Name: cvequery
Version: 1.0.6.post1
Summary: Query CVE details using Shodan's public CVE database API.
Home-page: https://github.com/n3th4ck3rx/cvequery
Author: Neo
Author-email: Neo <neo.nzso@proton.me>
License: MIT
Requires-Python: >=3.8
License-File: LICENSE
Requires-Dist: requests>=2.20.0
Requires-Dist: click>=6.0
Requires-Dist: colorama>=0.3.0
Requires-Dist: rich>=13.0.0
Requires-Dist: urllib3>=1.20
Requires-Dist: certifi
Requires-Dist: typing-extensions>=3.7.4
Provides-Extra: formats
Requires-Dist: PyYAML>=6.0.0; extra == "formats"
Requires-Dist: stix2>=3.0.0; extra == "formats"
Provides-Extra: all
Requires-Dist: PyYAML>=6.0.0; extra == "all"
Requires-Dist: stix2>=3.0.0; extra == "all"
Dynamic: author
Dynamic: home-page
Dynamic: license-file
Dynamic: requires-python
